README.md
setup.cfg
setup.py
versioneer.py
autophrase/.DS_Store
autophrase/Makefile
autophrase/__init__.py
autophrase/_version.py
autophrase/auto_phrase.sh
autophrase/autophrase.py
autophrase/compile.sh
autophrase/phrasal_segmentation.sh
autophrase/pos_tag.py
autophrase/test.py
autophrase/wiki_url.py
autophrase.egg-info/PKG-INFO
autophrase.egg-info/SOURCES.txt
autophrase.egg-info/dependency_links.txt
autophrase.egg-info/top_level.txt
autophrase/__pycache__/__init__.cpython-38.pyc
autophrase/__pycache__/_version.cpython-38.pyc
autophrase/__pycache__/autophrase.cpython-38.pyc
autophrase/__pycache__/pos_tag.cpython-38.pyc
autophrase/__pycache__/wiki_url.cpython-38.pyc
autophrase/bin/segphrase_segment
autophrase/bin/segphrase_train
autophrase/data/BAD_POS_TAGS.txt
autophrase/data/CN/paper.txt
autophrase/data/CN/stopwords.txt
autophrase/data/CN/wiki_all.txt
autophrase/data/CN/wiki_quality.txt
autophrase/data/EN/DBLP.5K.txt
autophrase/data/EN/stopwords.txt
autophrase/data/EN/wiki_all.txt
autophrase/data/EN/wiki_quality.txt
autophrase/data/ErrTest/test.txt
autophrase/data/JA/stopwords.txt
autophrase/data/JA/wiki_all.txt
autophrase/data/JA/wiki_quality.txt
autophrase/docker/Dockerfile
autophrase/docker/make.sh
autophrase/src/.DS_Store
autophrase/src/main.cpp
autophrase/src/segment.cpp
autophrase/src/classification/feature_extraction.h
autophrase/src/classification/label_generation.h
autophrase/src/classification/predict_quality.h
autophrase/src/classification/random_forest.h
autophrase/src/clustering/clustering.h
autophrase/src/data/documents.h
autophrase/src/data/dump.h
autophrase/src/frequent_pattern_mining/frequent_pattern_mining.h
autophrase/src/model_training/segmentation.h
autophrase/src/utils/commandline_flags.h
autophrase/src/utils/parameters.h
autophrase/src/utils/random.h
autophrase/src/utils/utils.h
autophrase/tmp/case_tokenized_train.txt
autophrase/tmp/language.txt
autophrase/tmp/pos_tags_tokenized_train.txt
autophrase/tmp/raw_tokenized_all.txt
autophrase/tmp/raw_tokenized_quality.txt
autophrase/tmp/raw_tokenized_stopwords.txt
autophrase/tmp/token_mapping.txt
autophrase/tmp/tokenized_all.txt
