Metadata-Version: 1.2
Name: autophrase
Version: 1.7
Summary: Automated Phrase Mining from Massive Text Corpora
Home-page: https://github.com/shangjingbo1226/AutoPhrase
Author: 
Author-email: 
License: UNKNOWN
Project-URL: Bug Reports, https://github.com/shangjingbo1226/AutoPhrase/issues
Keywords: phrase mining
Platform: UNKNOWN
Classifier: Development Status :: 3 - Alpha
Classifier: Intended Audience :: Developers
Classifier: License :: OSI Approved :: MIT License
Classifier: Programming Language :: Python :: 3
Classifier: Programming Language :: Python :: 3.4
Classifier: Programming Language :: Python :: 3.5
Classifier: Programming Language :: Python :: 3.6
